peaqoffpeak/__init__.py
peaqoffpeak/const.py
peaqoffpeak/service.py
peaqoffpeak/svk_repository.py
peaqoffpeak/models/__init__.py
peaqoffpeak/models/consumptionprofile_dto.py
peaqoffpeak/models/consumptionprofile_model.py
peaqoffpeak/models/consumptionprofile_rq.py
peaqoffpeak/models/networkarea_dto.py
peaqoffpeak/models/networkarea_model.py
peaqoffpeak-0.1.3.dist-info/METADATA
peaqoffpeak-0.1.3.dist-info/WHEEL
peaqoffpeak-0.1.3.dist-info/top_level.txt
peaqoffpeak-0.1.3.dist-info/RECORD
