Metadata-Version: 2.1
Name: peaqoffpeak
Version: 0.1.3
Summary: Partial wrapper for Svk Mimer Api
Author: Magnus Eldén
License: CC-NC-ND
Requires-Dist: requests
